webcv/__init__.py
webcv/manager.py
webcv/server.py
webcv/templates/index.html
webcv-1.0.3.dist-info/LICENSE
webcv-1.0.3.dist-info/METADATA
webcv-1.0.3.dist-info/WHEEL
webcv-1.0.3.dist-info/top_level.txt
webcv-1.0.3.dist-info/RECORD
