Metadata-Version: 2.1
Name: webcv
Version: 1.0.3
Summary: "A web wrapper for opencv that supports displaying via web browsers."
Home-page: https://github.com/wanzysky/webcv
Author: Zhaoyi Wan
Author-email: i@wanzy.me
License: UNKNOWN
Project-URL: Bug Tracker, https://github.com/pypa/sampleproject/issues
Platform: UNKNOWN
Classifier: Programming Language :: Python :: 3
Classifier: License :: OSI Approved :: MIT License
Classifier: Operating System :: OS Independent
Requires-Python: >=3.7
License-File: LICENSE
Requires-Dist: quart
Requires-Dist: opencv-python
